django_rest_exception_logger/__init__.py
django_rest_exception_logger/admin.py
django_rest_exception_logger/apps.py
django_rest_exception_logger/middleware.py
django_rest_exception_logger/models.py
django_rest_exception_logger/migrations/0001_initial.py
django_rest_exception_logger/migrations/__init__.py
tests/__init__.py
tests/test_middleware.py
django_rest_exception_logger-0.1.4.dist-info/LICENSE
django_rest_exception_logger-0.1.4.dist-info/METADATA
django_rest_exception_logger-0.1.4.dist-info/WHEEL
django_rest_exception_logger-0.1.4.dist-info/top_level.txt
django_rest_exception_logger-0.1.4.dist-info/RECORD
