Metadata-Version: 2.1
Name: django-rest-exception-logger
Version: 0.1.4
Summary: Automatic exception logging for Django applications.
Home-page: https://github.com/ErenErchamion/DjangoRestExceptionLogger
Author: Eren Berk Erkoç
Author-email: eren.erkoc.66@gmail.com
License: MIT
Classifier: Framework :: Django
Classifier: Programming Language :: Python :: 3
Classifier: License :: OSI Approved :: MIT License
License-File: LICENSE
Requires-Dist: Django >=3.2
Requires-Dist: djangorestframework >=3.12
